gematriapy/__init__.py
gematriapy/gematria.py
gematriapy-0.3.0.dist-info/LICENSE
gematriapy-0.3.0.dist-info/METADATA
gematriapy-0.3.0.dist-info/WHEEL
gematriapy-0.3.0.dist-info/top_level.txt
gematriapy-0.3.0.dist-info/RECORD
