Metadata-Version: 2.1
Name: gematriapy
Version: 0.3.0
Summary: Convert number to Hebrew or Hebrew to number
Home-page: https://github.com/NoamNol/gematriapy
Author: Noam Nol
Author-email: noamnol19@gmail.com
License: MIT
Keywords: hebrew gematria gematriapy
Classifier: Programming Language :: Python :: 3
Classifier: License :: OSI Approved :: MIT License
Classifier: Operating System :: OS Independent
Classifier: Development Status :: 4 - Beta
Requires-Python: >=3.7
License-File: LICENSE
